stellarcare/__init__.py
stellarcare/load_data/__init__.py
stellarcare/load_data/load_data.py
stellarcare/sql/__init__.py
stellarcare/sql/stellar.py
stellarcare-1.0.7.dist-info/LICENSE
stellarcare-1.0.7.dist-info/METADATA
stellarcare-1.0.7.dist-info/WHEEL
stellarcare-1.0.7.dist-info/top_level.txt
stellarcare-1.0.7.dist-info/RECORD
