Metadata-Version: 2.1
Name: stellarcare
Version: 1.0.7
Summary: A package with methods for analyzing the Optum Labs/UHC Stellar program
Home-page: https://github.com/optum-labs/stellar
Author: Nicole Sullivan
Author-email: nicolesullivan@optum.com
Project-URL: Bug Tracker, https://github.com/optum-labs/stellar/issues
Keywords: pilot,database,querying,analysis
Classifier: Programming Language :: Python :: 3
Classifier: License :: OSI Approved :: MIT License
Classifier: Operating System :: OS Independent
License-File: LICENSE
Requires-Dist: requests
Requires-Dist: importlib-metadata
Requires-Dist: pandas
Requires-Dist: datetime
Requires-Dist: teradatasql
